{"errorCode":"0000","errorTitle":"ثبت موفق","success":true,"type":"symbol","tagPosts":4,"tagFollows":5,"id":"IRK1K00499C1","InsCode":"10427474943853556","pushId":"SYMBOL_سکه9912پ04","name":"سکه9912پ04","title":"سکه9912پ04","corpName":"سکه تمام بهارتحویل1روزه صادرات","sectionName":"سرمایه گذاریها","subSectionName":"سایر واسطه های  مالی","status":"I","date":"1398/04/26 15:29:56","q_status":"","tradeCount":359,"tradeVolume":50050,"tradeTotalPrice":197830263920,"maxPrice":4110000,"minPrice":3870961,"firstPrice":3870961,"closingPrice":3952653,"lastPrice":4110000,"yesterdayPrice":4074695,"bestLimits":[{"buyVolume":50,"buyCount":1,"buyPrice":4120000,"sellPrice":4129999,"sellCount":2,"sellVolume":20},{"buyVolume":100,"buyCount":1,"buyPrice":4082500,"sellPrice":4130000,"sellCount":1,"sellVolume":50},{"buyVolume":100,"buyCount":1,"buyPrice":4082000,"sellPrice":4139999,"sellCount":1,"sellVolume":50}],"sellCountInd":67,"sellCountCorp":4,"sellVolumeInd":48000,"sellVolumeCorp":2050,"buyCountInd":110,"buyCountCorp":8,"buyVolumeInd":13870,"buyVolumeCorp":36180,"market":"بورس کالا","baseVolume":1,"marketValue":16805099494800,"totalCount":4251600,"minAllowPrice":3870961,"maxAllowPrice":4278429,"minAllowVolume":1,"maxAllowVolume":10000,"estimatedEPS":0,"PE":"","sectorPE":0,"stockholders":[{"title":"ايجاددارايي درانبار","count":2900510.0,"percent":68.22,"change":-6000.0},{"title":"صندوق سرمايه گذاري پشتوانه طلاي لوتوس","count":267700.0,"percent":6.29,"change":1030.0},{"title":"صندوق.س.دراوراق بهادارمبتني برسكه طلاي كيان","count":160020.0,"percent":3.76,"change":0.0},{"title":"شركت سرمايه گذاري توسعه صنعت وتجارت-سهامي عام","count":150000.0,"percent":3.52,"change":27500.0},{"title":"صندوق.س.دراوراق بهادارمبتني برسكه طلاي مفيد","count":80150.0,"percent":1.88,"change":100.0}]}