{"errorCode":"0000","errorTitle":"ثبت موفق","success":true,"type":"symbol","tagPosts":362,"tagFollows":36,"id":"IRO7PESP0001","InsCode":"18346219759153870","pushId":"SYMBOL_شصفها","name":"شصفها","title":"شصفها","corpName":"پتروشیمی‌ اصفهان‌","sectionName":"محصولات شیمیایی","subSectionName":"تولید مواد شیمیایی پایه به جز کود","status":"IS","date":"1398/04/17 12:31:09","q_status":"","tradeCount":0,"tradeVolume":0,"tradeTotalPrice":0,"maxPrice":36000,"minPrice":36000,"firstPrice":36000,"closingPrice":36000,"lastPrice":36000,"yesterdayPrice":36000,"bestLimits":[{"buyVolume":1000,"buyCount":1,"buyPrice":34000,"sellPrice":38400,"sellCount":1,"sellVolume":2000},{"buyVolume":800,"buyCount":1,"buyPrice":28000,"sellPrice":38800,"sellCount":1,"sellVolume":2000},{"buyVolume":50000,"buyCount":1,"buyPrice":10000,"sellPrice":44000,"sellCount":1,"sellVolume":2829}],"sellCountInd":82,"sellCountCorp":1,"sellVolumeInd":1087908,"sellVolumeCorp":45000,"buyCountInd":321,"buyCountCorp":2,"buyVolumeInd":1131353,"buyVolumeCorp":1555,"market":"پایه فرابورس","baseVolume":1,"marketValue":10800000000000,"totalCount":300000000,"minAllowPrice":1,"maxAllowPrice":999999,"minAllowVolume":1,"maxAllowVolume":50000,"estimatedEPS":8664,"PE":4.1551246537,"sectorPE":0,"stockholders":[{"title":"شركت صنايع خودروسازي ماهوراسپادانا-سهامي خاص","count":1.03026174E8,"percent":34.34,"change":0.0},{"title":"صندوق بازنشستگي كشوري","count":6.6793054E7,"percent":22.26,"change":0.0},{"title":"شخص حقيقي","count":1.6352289E7,"percent":5.45,"change":0.0},{"title":"شخص حقيقي","count":1.5411368E7,"percent":5.13,"change":0.0},{"title":"شركت تجارت آذين نقش جهان-سهامي خاص-","count":1.0874443E7,"percent":3.62,"change":0.0},{"title":"شركت سرمايه گذاري بهمن-سهامي عام-","count":7283223.0,"percent":2.42,"change":0.0},{"title":"شركت گروه توسعه مالي مهرآيندگان-سهامي عام-","count":4104858.0,"percent":1.36,"change":0.0},{"title":"شخص حقيقي","count":3299095.0,"percent":1.09,"change":0.0}]}