{"errorCode":"0000","errorTitle":"ثبت موفق","success":true,"type":"symbol","tagPosts":2592,"tagFollows":56,"id":"IRO3DZLZ0001","InsCode":"38084304113529336","pushId":"SYMBOL_خدیزل","name":"خدیزل","title":"خدیزل","corpName":"بهمن دیزل","sectionName":"خودرو و ساخت قطعات","subSectionName":"تولید وسایل نقلیه موتوری","status":"A","date":"1398/04/26 12:29:59","q_status":"","tradeCount":315,"tradeVolume":2137967,"tradeTotalPrice":14178086335,"maxPrice":6831,"minPrice":6181,"firstPrice":6492,"closingPrice":6632,"lastPrice":6700,"yesterdayPrice":6506,"bestLimits":[{"buyVolume":240,"buyCount":1,"buyPrice":6612,"sellPrice":6699,"sellCount":1,"sellVolume":3520},{"buyVolume":780,"buyCount":1,"buyPrice":6603,"sellPrice":6700,"sellCount":1,"sellVolume":4270},{"buyVolume":2000,"buyCount":1,"buyPrice":6550,"sellPrice":6728,"sellCount":1,"sellVolume":40000}],"sellCountInd":91,"sellCountCorp":4,"sellVolumeInd":1557861,"sellVolumeCorp":580106,"buyCountInd":86,"buyCountCorp":3,"buyVolumeInd":1782327,"buyVolumeCorp":355640,"market":"فرابورس","baseVolume":1,"marketValue":6632000000000,"totalCount":1000000000,"minAllowPrice":6181,"maxAllowPrice":6831,"minAllowVolume":1,"maxAllowVolume":50000,"estimatedEPS":566,"PE":11.7173144876,"sectorPE":20.27,"stockholders":[{"title":"شركت گروه بهمن-سهامي عام-","count":8.87615726E8,"percent":88.76,"change":0.0}]}