{"result":[{"status":"A","qStatus":"N","index_affect":0,"index_affect_rank":0,"alerts":null,"PE":-3.6937269372693726,"sectorPE":0,"profit7Days":0,"profit30Days":5.04,"profit91Days":27.35,"profit182Days":5.37,"profit365Days":1.93,"profitAllDays":92.13,"monthProfitRank":267,"monthProfitRankGroup":15,"marketValueRank":494,"marketValueRankGroup":17,"tradeVolumeRank":364,"tradeVolumeRankGroup":16,"zaribNaghdShavandegi":11.07,"correlation_dollar":-56.37,"correlation_ons_tala":83.21,"correlation_oil_opec":6.06,"correlation_main_index":80.76,"sahamayb_post_count":1,"sahamayb_post_count_rank":508.0,"sahamyab_follower_count_rank":656,"sahamyab_page_visit_rank":608}],"success":true}