{"errorCode":"0000","errorTitle":"ثبت موفق","success":true,"type":"symbol","tagPosts":3607,"tagFollows":68,"id":"IRO3PKDZ0001","InsCode":"3492952121304423","pushId":"SYMBOL_غدیس","name":"غدیس","title":"غدیس","corpName":"پاکدیس","sectionName":"محصولات غذایی و آشامیدنی به جز قند و شکر","subSectionName":"تولید نوشیدنی و آبمیوه","status":"A","date":"1398/04/26 13:20:45","q_status":"sell","tradeCount":404,"tradeVolume":1871156,"tradeTotalPrice":21090096488,"maxPrice":12000,"minPrice":11171,"firstPrice":11171,"closingPrice":11271,"lastPrice":11171,"yesterdayPrice":11758,"bestLimits":[{"buyVolume":0,"buyCount":0,"buyPrice":0,"sellPrice":11171,"sellCount":4,"sellVolume":5951},{"buyVolume":0,"buyCount":0,"buyPrice":0,"sellPrice":11389,"sellCount":1,"sellVolume":6220},{"buyVolume":0,"buyCount":0,"buyPrice":0,"sellPrice":11390,"sellCount":2,"sellVolume":2532}],"sellCountInd":93,"sellCountCorp":4,"sellVolumeInd":1382031,"sellVolumeCorp":489125,"buyCountInd":130,"buyCountCorp":1,"buyVolumeInd":1771156,"buyVolumeCorp":100000,"market":"فرابورس","baseVolume":1,"marketValue":3155880000000,"totalCount":280000000,"minAllowPrice":11171,"maxAllowPrice":12345,"minAllowVolume":1,"maxAllowVolume":50000,"estimatedEPS":296,"PE":38.0777027027,"sectorPE":19.11,"stockholders":[{"title":"شركت مادرتخصصي گسترش صنايع غذايي سينا-سهامي خا","count":1.25050001E8,"percent":44.66,"change":0.0},{"title":"بنيادمستضعفان انقلاب اسلامي","count":1.11136328E8,"percent":39.69,"change":0.0},{"title":"شركت سرمايه گذاري سايه گسترسرمايه-سهامي خاص-","count":5210003.0,"percent":1.86,"change":0.0},{"title":"شركت مادرتخصصي مالي وسرمايه گذاري سينا-سهامي خ","count":3593019.0,"percent":1.28,"change":0.0},{"title":"شخص حقيقي","count":2970411.0,"percent":1.06,"change":0.0}]}