{"errorCode":"0000","errorTitle":"ثبت موفق","success":true,"type":"symbol","tagPosts":15,"tagFollows":1,"id":"IRR3KHZZ0101","InsCode":"22542452157560209","pushId":"SYMBOL_حخزرح","name":"حخزرح","title":"حخزرح","corpName":"کشتیرانی دریای خزر","sectionName":"حمل و نقل آبی","subSectionName":"حمل و نقل دریایی وحمل ونقل درآبهای ساحلی","status":"IS","date":"1397/08/17 00:00:00","q_status":"","tradeCount":0,"tradeVolume":0,"tradeTotalPrice":0,"maxPrice":0,"minPrice":0,"firstPrice":0,"closingPrice":2460,"lastPrice":2400,"yesterdayPrice":0,"bestLimits":[],"sellCountInd":0,"sellCountCorp":0,"sellVolumeInd":0,"sellVolumeCorp":0,"buyCountInd":0,"buyCountCorp":0,"buyVolumeInd":0,"buyVolumeCorp":0,"market":"فرابورس","baseVolume":1,"marketValue":0,"totalCount":0,"minAllowPrice":2337,"maxAllowPrice":2583,"minAllowVolume":1,"maxAllowVolume":10000,"estimatedEPS":0,"PE":"","sectorPE":18.33,"stockholders":null}