{"errorCode":"0000","errorTitle":"ثبت موفق","success":true,"type":"symbol","tagPosts":16126,"tagFollows":594,"id":"IRO1RSAP0001","InsCode":"45174198424472334","pushId":"SYMBOL_ولساپا","name":"ولساپا","title":"ولساپا","corpName":"لیزینگ رایان‌ سایپا","sectionName":"سایر واسطه گریهای مالی","subSectionName":"لیزینگ  مالی","status":"A","date":"1398/04/26 12:29:57","q_status":"","tradeCount":1548,"tradeVolume":24121724,"tradeTotalPrice":31774764475,"maxPrice":1350,"minPrice":1283,"firstPrice":1350,"closingPrice":1317,"lastPrice":1305,"yesterdayPrice":1350,"bestLimits":[{"buyVolume":52838,"buyCount":4,"buyPrice":1304,"sellPrice":1306,"sellCount":1,"sellVolume":22937},{"buyVolume":15516,"buyCount":1,"buyPrice":1301,"sellPrice":1310,"sellCount":2,"sellVolume":58509},{"buyVolume":25000,"buyCount":5,"buyPrice":1300,"sellPrice":1311,"sellCount":1,"sellVolume":100000}],"sellCountInd":286,"sellCountCorp":0,"sellVolumeInd":24121724,"sellVolumeCorp":0,"buyCountInd":553,"buyCountCorp":3,"buyVolumeInd":21721724,"buyVolumeCorp":2400000,"market":"بورس","baseVolume":1,"marketValue":11905680000000,"totalCount":9040000000,"minAllowPrice":1283,"maxAllowPrice":1417,"minAllowVolume":1,"maxAllowVolume":100000,"estimatedEPS":227,"PE":5.8017621145,"sectorPE":7.34,"stockholders":[{"title":"شركت ايراني توليداتومبيل-سايپا-","count":3.014755428E9,"percent":33.34,"change":0.0},{"title":"شركت سايپا","count":1.545530659E9,"percent":17.09,"change":0.0},{"title":"شركت ايراني توليداتومبيل سايپا-سهامي عام-","count":4.54E8,"percent":5.02,"change":0.0},{"title":"شركت سرمايه گذاري وتوسعه صنعتي نيوان ابتكارس.ع","count":4.09843922E8,"percent":4.53,"change":0.0},{"title":"شركت گروه مالي سپهرصادرات-سهامي خاص-","count":1.644E8,"percent":1.81,"change":0.0},{"title":"شركت سايان توسعه سرمايه گذار-سهامي خاص-","count":1.26826988E8,"percent":1.4,"change":0.0},{"title":"شركت رايان سايپا-سهامي خاص-","count":1.13173012E8,"percent":1.25,"change":0.0},{"title":"شركت گروه سرمايه گذاري كاركنان سايپا-سهامي خاص","count":9.6763732E7,"percent":1.07,"change":0.0}]}