{"result":[[{"code":"موضوع فعالیت :","title":"توليد سيمان خاکستري ؛ بهره برداري از ذخاير معدني ؛ خريد و فروش مصالح ساختماني ؛ اجاره يا خريد معادن ؛ خريد و فروش انواع سيمان ؛ توليد و فروش انواع سيمان ؛ صادرات و واردات از کالاهاي مورد نياز"},{"code":"مدیر عامل :","title":"محمد رباني"},{"code":"نشانی :","title":"کيلومتر 32 جاده کرمان – تهران"},{"code":"شماره تلفن :","title":"33370561"},{"code":"نمابر :","title":"33370563"},{"code":"نشانی دفتر :","title":"کيلومتر 32 جاده کرمان – تهران"},{"code":"نشانی امور سهام :","title":"کيلومتر 32 جاده کرمان – تهران"},{"code":"وب سایت :","title":"www.momtazancement.com"},{"code":"ایمیل :","title":"info@momtazancement.com"},{"code":"حسابرس :","title":"موسسه حسابرسي و خدمات مديريت آزموده کاران"},{"code":"سرمایه :","title":"600000"},{"code":"سال مالی :","title":"12/29"},{"code":"مدیر مالی :","title":"حسین قلیزاده حسین آبادی"},{"code":"شناسه ملی :","title":"10860238958"}]],"success":true}