{"result":[[{"code":"موضوع فعالیت :","title":"توليد شکر وتوليدوتصفيه  شکر خام و متفرعات آن"},{"code":"مدیر عامل :","title":"آقاي مهندس غلامعباس بهمني"},{"code":"نشانی :","title":"خراسان رضوي - کيلومتر 12 جاده تربت جام به تايباد - روبروي پليس راه"},{"code":"شماره تلفن :","title":"52963305-051"},{"code":"نمابر :","title":"52963316-051"},{"code":"نشانی دفتر :","title":"تهران - خيابان فاطمي - خيابان پروين اعتصامي -پلاک 72"},{"code":"نشانی امور سهام :","title":"خراسان رضوي - کيلومتر 12 جاده تربت جام به تايباد - روبروي پليس راه"},{"code":"وب سایت :","title":"www.agahantaraz.com"},{"code":"ایمیل :","title":"info@agahantaraz.com"},{"code":"حسابرس :","title":"موسسه حسابرسي ديلمي پور و همکاران (حسابداران رسمي)"},{"code":"سرمایه :","title":"312000"},{"code":"سال مالی :","title":"03/31"},{"code":"مدیر مالی :","title":"محمد رضا اخوان"},{"code":"شناسه ملی :","title":"10380025768"}]],"success":true}