{"result":[[{"code":"موضوع فعالیت :","title":"1ـافتتاح و نگهداري انواع سپرده هاي قرض الحسنه جاري ، پس انداز و سپرده هاي کوتاه مدت و بلندمدت و ساير حساب هاي مشابه و صدور گواهي سپرده عام و خاص 2- انجام عمليات اعتباري مصرح در قانون عمليات بانکي بدون ربا 3- ارائه انواع خدمات بانکي"},{"code":"مدیر عامل :","title":"رضا دولت آبادي"},{"code":"نشانی :","title":""},{"code":"شماره تلفن :","title":"021-81041"},{"code":"نمابر :","title":"021-88822950"},{"code":"نشانی دفتر :","title":"خ طالقاني -نبش استاد نجات الهي-شماره 247"},{"code":"نشانی امور سهام :","title":"خ طالقاني - نرسيده به حافظ- شماره 402 -مديريت امور مالي بانک تجارت - طبقه اول"},{"code":"وب سایت :","title":"www.tejarat.ir"},{"code":"ایمیل :","title":"info@tejaratbank.ir"},{"code":"حسابرس :","title":"سازمان حسابرسي"},{"code":"سرمایه :","title":"223926127"},{"code":"سال مالی :","title":"12/29"},{"code":"مدیر مالی :","title":"امين پوربهبهاني"},{"code":"شناسه ملی :","title":"10100834460"}]],"success":true}