{"errorCode":"0000","errorTitle":"ثبت موفق","success":true,"type":"symbol","tagPosts":14499,"tagFollows":140,"id":"IRO7RAHP0001","InsCode":"30443839313522574","pushId":"SYMBOL_حرهشا","name":"حرهشا","title":"حرهشا","corpName":"رهشاد سپاهان (سهامی عام","sectionName":"حمل ونقل، انبارداری و ارتباطات","subSectionName":"سایر حمل و نقلهای زمینی برنامه ریزی شده","status":"IS","date":"1398/04/26 12:30:12","q_status":"","tradeCount":529,"tradeVolume":1195293,"tradeTotalPrice":30319405652,"maxPrice":25652,"minPrice":22091,"firstPrice":24400,"closingPrice":25366,"lastPrice":25652,"yesterdayPrice":23320,"bestLimits":[{"buyVolume":46523,"buyCount":2,"buyPrice":25652,"sellPrice":25900,"sellCount":1,"sellVolume":1000},{"buyVolume":98,"buyCount":1,"buyPrice":25650,"sellPrice":26000,"sellCount":1,"sellVolume":1000},{"buyVolume":14000,"buyCount":2,"buyPrice":25625,"sellPrice":26199,"sellCount":1,"sellVolume":500}],"sellCountInd":181,"sellCountCorp":0,"sellVolumeInd":1195293,"sellVolumeCorp":0,"buyCountInd":172,"buyCountCorp":3,"buyVolumeInd":1006257,"buyVolumeCorp":189036,"market":"پایه فرابورس","baseVolume":1,"marketValue":380490000000,"totalCount":15000000,"minAllowPrice":20988,"maxAllowPrice":25652,"minAllowVolume":1,"maxAllowVolume":50000,"estimatedEPS":636,"PE":39.8836477987,"sectorPE":0,"stockholders":[{"title":"شركت مهندسي كاوه پوشش بناساز-سهامي خاص-","count":949000,"percent":6.32,"change":1800},{"title":"شخص حقيقي","count":602487,"percent":4.01,"change":0},{"title":"شخص حقيقي","count":572411,"percent":3.81,"change":0},{"title":"شخص حقيقي","count":433839,"percent":2.89,"change":0},{"title":"شخص حقيقي","count":400508,"percent":2.67,"change":8},{"title":"شخص حقيقي","count":367572,"percent":2.45,"change":0},{"title":"شخص حقيقي","count":364651,"percent":2.43,"change":0},{"title":"شخص حقيقي","count":257907,"percent":1.71,"change":0},{"title":"شخص حقيقي","count":174193,"percent":1.16,"change":534},{"title":"شخص حقيقي","count":164650,"percent":1.09,"change":0},{"title":"شخص حقيقي","count":164445,"percent":1.09,"change":0},{"title":"شخص حقيقي","count":163200,"percent":1.08,"change":0},{"title":"شخص حقيقي","count":162620,"percent":1.08,"change":0}]}