{"result":[[{"code":"موضوع فعالیت :","title":"انبوه سازي و املاک و سرمايه گذاريها"},{"code":"مدیر عامل :","title":"يوسف  صفارشاهرودي"},{"code":"نشانی :","title":""},{"code":"شماره تلفن :","title":"02188704777"},{"code":"نمابر :","title":"02186046719"},{"code":"نشانی دفتر :","title":"تهران - خيابان ميرزاي شيرازي بالاتر از خيابان شهيد مطهري - کوچه شهدا - پلاک 21"},{"code":"نشانی امور سهام :","title":"تهران - خيابان ميرزاي شيرازي بالاتر از خيابان شهيد مطهري - کوچه شهدا - پلاک 21"},{"code":"وب سایت :","title":"www.nosa-eng.com"},{"code":"ایمیل :","title":"nosa.iran@gmail.com"},{"code":"حسابرس :","title":"موسسه حسابرسي و خدمات مديريت اصول پايه فراگير"},{"code":"سرمایه :","title":"2630000"},{"code":"سال مالی :","title":"06/31"},{"code":"مدیر مالی :","title":"احسان صادقی"},{"code":"شناسه ملی :","title":"10101683349"}]],"success":true}