{"errorCode":"0000","errorTitle":"ثبت موفق","success":true,"type":"symbol","tagPosts":8221,"tagFollows":477,"id":"IRO1PABD0001","InsCode":"11640540339380126","pushId":"SYMBOL_شپترو","name":"شپترو","title":"شپترو","corpName":"پتروشیمی‌ آبادان‌","sectionName":"محصولات شیمیایی","subSectionName":"تولید پلاستیک اولیه و لاستیک ترکیبی","status":"IS","date":"1398/04/22 12:52:19","q_status":"","tradeCount":0,"tradeVolume":0,"tradeTotalPrice":0,"maxPrice":1475,"minPrice":1414,"firstPrice":1447,"closingPrice":1446,"lastPrice":1452,"yesterdayPrice":1446,"bestLimits":[{"buyVolume":13921,"buyCount":1,"buyPrice":1430,"sellPrice":1460,"sellCount":1,"sellVolume":10000},{"buyVolume":42600,"buyCount":1,"buyPrice":1400,"sellPrice":1467,"sellCount":1,"sellVolume":50000},{"buyVolume":1000,"buyCount":1,"buyPrice":1370,"sellPrice":1470,"sellCount":1,"sellVolume":1205}],"sellCountInd":976,"sellCountCorp":2,"sellVolumeInd":30510163,"sellVolumeCorp":209000,"buyCountInd":609,"buyCountCorp":0,"buyVolumeInd":30719163,"buyVolumeCorp":0,"market":"بورس","baseVolume":1,"marketValue":5089920000000,"totalCount":3520000000,"minAllowPrice":1374,"maxAllowPrice":1518,"minAllowVolume":1,"maxAllowVolume":100000,"estimatedEPS":-226.0,"PE":-6.398230088495575,"sectorPE":7.15,"stockholders":[{"title":"شركت سرمايه گذاري نفت وگازوپتروشيمي تامين-س.ع","count":1902817414,"percent":54.05,"change":0},{"title":"شركت.س.صندوق بازنشستگي كشوري-سهامي عام-","count":291341269,"percent":8.27,"change":0}]}