{"result":[[{"code":"موضوع فعالیت :","title":"توليد ورق موجدار  و لوله چهارگوش ساختماني بدون آزبست"},{"code":"مدیر عامل :","title":"سيد محمد رضا موسوي چهارده"},{"code":"نشانی :","title":"دورودلرستان -ميدان خاتم الانبياء"},{"code":"شماره تلفن :","title":"2-88740791"},{"code":"نمابر :","title":"88740756=88759968"},{"code":"نشانی دفتر :","title":""},{"code":"نشانی امور سهام :","title":"تهران - خيابان دکتر بهشتي - خيابان صابونچي - پلاک 24 جديد 48 قديم -طبقه دوم  - واحد 60"},{"code":"وب سایت :","title":""},{"code":"ایمیل :","title":"farsit.saham@yahoo.com"},{"code":"حسابرس :","title":"دايا رهيافت"},{"code":"سرمایه :","title":"120960"},{"code":"سال مالی :","title":"12/29"},{"code":"مدیر مالی :","title":""},{"code":"شناسه ملی :","title":"10740023815"}]],"success":true}