{"result":[{"status":"A","qStatus":"N","index_affect":0,"index_affect_rank":0,"alerts":null,"PE":18.8179551122,"sectorPE":0,"profit7Days":-5.14,"profit30Days":40.63,"profit91Days":35.91,"profit182Days":654.6,"profit365Days":"","profitAllDays":690.16,"monthProfitRank":74,"monthProfitRankGroup":3,"marketValueRank":344,"marketValueRankGroup":25,"tradeVolumeRank":321,"tradeVolumeRankGroup":18,"zaribNaghdShavandegi":33.09,"correlation_dollar":-45.66,"correlation_ons_tala":79.48,"correlation_oil_opec":10.06,"correlation_main_index":59.67,"sahamayb_post_count":8,"sahamayb_post_count_rank":250.0,"sahamyab_follower_count_rank":432,"sahamyab_page_visit_rank":341}],"success":true}