{"errorCode":"0000","errorTitle":"ثبت موفق","success":true,"type":"symbol","tagPosts":0,"tagFollows":0,"id":"IRO3MSZ96021","InsCode":"47245955682789926","pushId":"SYMBOL_تسه9602","name":"تسه9602","title":"تسه9602","corpName":"بانک مسکن","sectionName":"اوراق حق تقدم استفاده از تسهیلات مسکن","subSectionName":"اوراق حق تقدم استفاده از تسهیلات مسکن","status":"IS","date":"1398/02/15 12:27:07","q_status":"sell","tradeCount":0,"tradeVolume":0,"tradeTotalPrice":0,"maxPrice":376669,"minPrice":340797,"firstPrice":340797,"closingPrice":349536,"lastPrice":367030,"yesterdayPrice":349536,"bestLimits":[{"buyVolume":0,"buyCount":0,"buyPrice":0,"sellPrice":377613,"sellCount":1,"sellVolume":1},{"buyVolume":0,"buyCount":0,"buyPrice":0,"sellPrice":0,"sellCount":0,"sellVolume":0},{"buyVolume":0,"buyCount":0,"buyPrice":0,"sellPrice":0,"sellCount":0,"sellVolume":0}],"sellCountInd":99,"sellCountCorp":6,"sellVolumeInd":2173,"sellVolumeCorp":50,"buyCountInd":41,"buyCountCorp":0,"buyVolumeInd":2223,"buyVolumeCorp":0,"market":"فرابورس","baseVolume":1,"marketValue":457475163552,"totalCount":1308807,"minAllowPrice":332060,"maxAllowPrice":367012,"minAllowVolume":1,"maxAllowVolume":140,"estimatedEPS":0,"PE":"","sectorPE":0,"stockholders":[{"title":"تسهيلات استفاده شده بانك مسكن-ممنوع المعامله-","count":1270596.0,"percent":97.08,"change":0.0}]}