{"result":[[{"code":"موضوع فعالیت :","title":"خريدو واردات موتور ومواد اوليه وقطعات نيمه ساخته وساخته شده موتورهاي خودرو، صنعتي وکشاورزي وساير کاربردها وهمچنين توليد ونصب آنها به ادوات مختلف وفروش وصادرات آنها، واردات وساخت وخريد وفروش انواع ماشين آلات صنعتي وتجهيزات وساير صنايع مشابه ونصب وراه اندازي ومشاوره درانتخاب آنها، عقد هرگونه قرارداد بااشخاص حقيقي وحقوقي"},{"code":"مدیر عامل :","title":"محمد شهباز نجفعليزاد"},{"code":"نشانی :","title":"تبريز: جاده سردرود - گروه صنعتي تراکتورسازي ايران - شرکت موتورسازان"},{"code":"شماره تلفن :","title":"04134248000"},{"code":"نمابر :","title":"04134245945"},{"code":"نشانی دفتر :","title":"تهران: کيلومتر 5/9 جاده مخصوص کرج - روبروي شهاب خودرو - جنب پارس خودرو - خيابان نخ زرين - شرکت بازرگاني تراکتورسازي (تسکو)"},{"code":"نشانی امور سهام :","title":"تبريز: جاده سردرود - گروه صنعتي تراکتورسازي ايران - شرکت موتورسازان"},{"code":"وب سایت :","title":"www.motorsazan.ir"},{"code":"ایمیل :","title":"mail@motorsazan.ir"},{"code":"حسابرس :","title":"موسسه حسابرسي فراز مشاور"},{"code":"سرمایه :","title":"714420"},{"code":"سال مالی :","title":"12/29"},{"code":"مدیر مالی :","title":"مجید رسولی سقای"},{"code":"شناسه ملی :","title":"10200101232"}]],"success":true}