{"result":[[{"code":"موضوع فعالیت :","title":"توليد قطعات پلاستيکي صنعتي"},{"code":"مدیر عامل :","title":"آقاي حسين خسروشاهي اصل"},{"code":"نشانی :","title":"تهران کيلومتر 14 جاده قديم کرج ابتداي بلوار ايران خودرو"},{"code":"شماره تلفن :","title":"44923022-021"},{"code":"نمابر :","title":"44923027-021"},{"code":"نشانی دفتر :","title":"تهران خيابان انقلاب چهارراه کالج"},{"code":"نشانی امور سهام :","title":"تهران کيلومتر 14 جاده قديم کرج ابتداي بلوار ايران خودرو"},{"code":"وب سایت :","title":""},{"code":"ایمیل :","title":""},{"code":"حسابرس :","title":"موسسه حسابرسي مفيد راهبر"},{"code":"سرمایه :","title":"57600"},{"code":"سال مالی :","title":"12/29"},{"code":"مدیر مالی :","title":"حسین صفی خانی"},{"code":"شناسه ملی :","title":"10100484677"}]],"success":true}