{"errorCode":"0000","errorTitle":"ثبت موفق","success":true,"type":"symbol","tagPosts":22,"tagFollows":6,"id":"IRO7CMKP0001","InsCode":"58035444268544991","pushId":"SYMBOL_سمتاز","name":"سمتاز","title":"سمتاز","corpName":"سیمان ممتازان کرمان","sectionName":"سیمان، آهک و گچ","subSectionName":"تولید سیمان، آهک و گچ","status":"A","date":"1398/04/26 12:31:20","q_status":"","tradeCount":10,"tradeVolume":43619,"tradeTotalPrice":364775800,"maxPrice":9336,"minPrice":8200,"firstPrice":9336,"closingPrice":8363,"lastPrice":8200,"yesterdayPrice":9336,"bestLimits":[{"buyVolume":2935,"buyCount":1,"buyPrice":8200,"sellPrice":9000,"sellCount":1,"sellVolume":600},{"buyVolume":2157,"buyCount":1,"buyPrice":8100,"sellPrice":9250,"sellCount":1,"sellVolume":3315},{"buyVolume":1000,"buyCount":1,"buyPrice":7001,"sellPrice":9290,"sellCount":1,"sellVolume":5000}],"sellCountInd":4,"sellCountCorp":0,"sellVolumeInd":43619,"sellVolumeCorp":0,"buyCountInd":6,"buyCountCorp":0,"buyVolumeInd":43619,"buyVolumeCorp":0,"market":"پایه فرابورس","baseVolume":1,"marketValue":5017800000000,"totalCount":600000000,"minAllowPrice":1,"maxAllowPrice":999999,"minAllowVolume":1,"maxAllowVolume":50000,"estimatedEPS":1061,"PE":7.8821866164,"sectorPE":0,"stockholders":[{"title":"شركت سيمان كرمان","count":2.22691316E8,"percent":37.11,"change":0.0},{"title":"شخص حقيقي","count":1.90405E7,"percent":3.17,"change":0.0},{"title":"شخص حقيقي","count":1.8014404E7,"percent":3.0,"change":0.0},{"title":"شخص حقيقي","count":1.3519999E7,"percent":2.25,"change":0.0},{"title":"شخص حقيقي","count":1.3479999E7,"percent":2.24,"change":0.0},{"title":"شخص حقيقي","count":1.3235157E7,"percent":2.2,"change":0.0},{"title":"شخص حقيقي","count":1.0957722E7,"percent":1.82,"change":0.0},{"title":"شخص حقيقي","count":1.016835E7,"percent":1.69,"change":0.0},{"title":"شخص حقيقي","count":9445117.0,"percent":1.57,"change":0.0},{"title":"شخص حقيقي","count":9199999.0,"percent":1.53,"change":0.0},{"title":"شخص حقيقي","count":9199999.0,"percent":1.53,"change":0.0},{"title":"شخص حقيقي","count":8720633.0,"percent":1.45,"change":0.0},{"title":"شخص حقيقي","count":8471839.0,"percent":1.41,"change":0.0},{"title":"شخص حقيقي","count":8022956.0,"percent":1.33,"change":0.0},{"title":"شخص حقيقي","count":7999999.0,"percent":1.33,"change":0.0},{"title":"شخص حقيقي","count":7999999.0,"percent":1.33,"change":0.0},{"title":"شخص حقيقي","count":7999999.0,"percent":1.33,"change":0.0},{"title":"شخص حقيقي","count":7999999.0,"percent":1.33,"change":0.0},{"title":"شخص حقيقي","count":7999999.0,"percent":1.33,"change":0.0},{"title":"شخص حقيقي","count":6538316.0,"percent":1.08,"change":0.0},{"title":"شخص حقيقي","count":6235494.0,"percent":1.03,"change":0.0},{"title":"شخص حقيقي","count":6117306.0,"percent":1.01,"change":0.0}]}