{"errorCode":"0000","errorTitle":"ثبت موفق","success":true,"type":"symbol","tagPosts":18891,"tagFollows":252,"id":"IRO1NALM0001","InsCode":"57875847776839336","pushId":"SYMBOL_فنوال","name":"فنوال","title":"فنوال","corpName":"نورد آلومینیوم‌","sectionName":"فلزات اساسی","subSectionName":"تولید فلزات گرانبهای غیرآهن","status":"IS","date":"1398/04/25 12:26:41","q_status":"","tradeCount":0,"tradeVolume":0,"tradeTotalPrice":0,"maxPrice":3977,"minPrice":3741,"firstPrice":3977,"closingPrice":3753,"lastPrice":3741,"yesterdayPrice":3753,"bestLimits":[{"buyVolume":800,"buyCount":1,"buyPrice":3250,"sellPrice":3742,"sellCount":1,"sellVolume":500},{"buyVolume":2000,"buyCount":1,"buyPrice":2366,"sellPrice":3795,"sellCount":1,"sellVolume":500},{"buyVolume":851,"buyCount":1,"buyPrice":2338,"sellPrice":3796,"sellCount":1,"sellVolume":500}],"sellCountInd":83,"sellCountCorp":0,"sellVolumeInd":1601843,"sellVolumeCorp":0,"buyCountInd":160,"buyCountCorp":0,"buyVolumeInd":1601843,"buyVolumeCorp":0,"market":"بورس","baseVolume":1,"marketValue":2545836291000,"totalCount":678347000,"minAllowPrice":3566,"maxAllowPrice":3940,"minAllowVolume":1,"maxAllowVolume":50000,"estimatedEPS":187,"PE":20.0695187166,"sectorPE":5.74,"stockholders":[{"title":"شركت آلومينيوم تابنده اراك-سهامي خاص-","count":1.08876809E8,"percent":16.05,"change":0.0},{"title":"شركت مدبرتجارت آريا-بامسئوليت محدود-","count":6.7E7,"percent":9.87,"change":0.0},{"title":"شركت پرتوكالاپرديس-بامسئوليت محدود-","count":5.7E7,"percent":8.4,"change":0.0},{"title":"شخص حقيقي","count":5.105E7,"percent":7.52,"change":0.0},{"title":"شخص حقيقي","count":3.6802354E7,"percent":5.42,"change":0.0},{"title":"شخص حقيقي","count":2.954755E7,"percent":4.35,"change":0.0},{"title":"شخص حقيقي","count":2.2857713E7,"percent":3.36,"change":0.0},{"title":"شخص حقيقي","count":2.2851063E7,"percent":3.36,"change":0.0},{"title":"شخص حقيقي","count":2.2846939E7,"percent":3.36,"change":0.0},{"title":"شخص حقيقي","count":2.2824354E7,"percent":3.36,"change":0.0},{"title":"شركت پيشران سرمايه پرديس-بامسئوليت محدود-","count":1.9651E7,"percent":2.89,"change":0.0},{"title":"شركت هوشمندسرمايه پرديس-بامسئوليت محدود-","count":1.8551E7,"percent":2.73,"change":0.0},{"title":"شركت تابان پروفيل پرديس-سهامي خاص-","count":1.6651E7,"percent":2.45,"change":0.0},{"title":"شخص حقيقي","count":1.4748451E7,"percent":2.17,"change":0.0},{"title":"شخص حقيقي","count":1.3587E7,"percent":2.0,"change":0.0},{"title":"شخص حقيقي","count":1.2131943E7,"percent":1.78,"change":0.0}]}