{"errorCode":"0000","errorTitle":"ثبت موفق","success":true,"type":"symbol","tagPosts":13274,"tagFollows":310,"id":"IRO3TORZ0001","InsCode":"37389789764168256","pushId":"SYMBOL_توریل","name":"توریل","title":"توریل","corpName":"توکاریل","sectionName":"حمل ونقل، انبارداری و ارتباطات","subSectionName":"حمل و نقل از طریق خطوط راه آهن","status":"A","date":"1398/04/26 12:29:51","q_status":"","tradeCount":1277,"tradeVolume":6044674,"tradeTotalPrice":27895090768,"maxPrice":4779,"minPrice":4472,"firstPrice":4472,"closingPrice":4615,"lastPrice":4672,"yesterdayPrice":4705,"bestLimits":[{"buyVolume":1284,"buyCount":1,"buyPrice":4650,"sellPrice":4700,"sellCount":1,"sellVolume":5000},{"buyVolume":6500,"buyCount":1,"buyPrice":4560,"sellPrice":4705,"sellCount":1,"sellVolume":7000},{"buyVolume":1106,"buyCount":1,"buyPrice":4540,"sellPrice":4713,"sellCount":1,"sellVolume":12900}],"sellCountInd":234,"sellCountCorp":3,"sellVolumeInd":5849854,"sellVolumeCorp":194820,"buyCountInd":540,"buyCountCorp":3,"buyVolumeInd":5811096,"buyVolumeCorp":233578,"market":"فرابورس","baseVolume":1,"marketValue":9230000000000,"totalCount":2000000000,"minAllowPrice":4470,"maxAllowPrice":4940,"minAllowVolume":1,"maxAllowVolume":100000,"estimatedEPS":817,"PE":5.6487148103,"sectorPE":8.33,"stockholders":[{"title":"شركت سرمايه گذاري توكافولاد-سهامي عام-","count":7.57615105E8,"percent":37.88,"change":0.0},{"title":"شركت سرمايه گذاري تامين اجتماعي نيروهاي مسلح-س","count":6.69502148E8,"percent":33.47,"change":0.0},{"title":"شركت حمل ونقل توكا-سهامي عام-","count":8.0760001E7,"percent":4.03,"change":0.0},{"title":"شركت سرمايه گذاري توسعه توكا-سهامي خاص-","count":3.02E7,"percent":1.51,"change":0.0},{"title":"شركت سرمايه گذاري مهرگان تامين پارس-سهامي خاص-","count":2.9739062E7,"percent":1.48,"change":0.0}]}